files_vector_mcp_server/__init__.py
files_vector_mcp_server/__main__.py
files_vector_mcp_server/main.py
files_vector_mcp_server/config/__init__.py
files_vector_mcp_server/config/settings.py
files_vector_mcp_server/services/__init__.py
files_vector_mcp_server/services/database.py
files_vector_mcp_server/services/file_processor.py
files_vector_mcp_server/utils/__init__.py
files_vector_mcp_server/utils/events.py
files_vector_mcp_server/utils/helpers.py
files_vector_mcp_server/utils/task_queue.py
files_vector_mcp_server-0.1.14.dist-info/licenses/LICENSE
files_vector_mcp_server-0.1.14.dist-info/METADATA
files_vector_mcp_server-0.1.14.dist-info/WHEEL
files_vector_mcp_server-0.1.14.dist-info/entry_points.txt
files_vector_mcp_server-0.1.14.dist-info/top_level.txt
files_vector_mcp_server-0.1.14.dist-info/RECORD
