Metadata-Version: 2.4
Name: files-vector-mcp-server
Version: 0.1.14
Summary: A FastMCP server for file vectorization and similarity search
Author-email: Your Name <your.email@example.com>
Project-URL: Homepage, https://github.com/928871247/files-vector-mcp-server
Project-URL: Bug Tracker, https://github.com/928871247/files-vector-mcp-server/issues
Keywords: mcp,vector-search,embeddings
Requires-Python: >=3.8
License-File: LICENSE
Requires-Dist: fastmcp>=0.5.0
Requires-Dist: psycopg2-binary>=2.9.6
Requires-Dist: openai>=1.0.0
Requires-Dist: python-dotenv>=1.0.0
Requires-Dist: python-docx>=0.8.11
Requires-Dist: PyPDF2>=3.0.1
Requires-Dist: python-pptx>=0.6.23
Requires-Dist: requests>=2.31.0
Requires-Dist: watchdog>=6.0.0
Dynamic: license-file
